{
  "pmid": "12779161",
  "uid": "12779161",
  "title": "Electromagnetically induced transparency due to intervalence band coherence in a GaAs quantum well.",
  "abstract": "We demonstrate electromagnetically induced transparency in the transient optical response in a GaAs quantum well by using the nonradiative coherence between the heavy-hole and the light-hole valence bands.",
  "authors": [
    {
      "last_name": "Phillips",
      "fore_name": "Mark",
      "initials": "M",
      "name": "Mark Phillips",
      "affiliations": [
        "Department of Physics and Oregon Center for Optics, University of Oregon, Eugene, Oregon 97403, USA."
      ]
    },
    {
      "last_name": "Wang",
      "fore_name": "Hailin",
      "initials": "H",
      "name": "Hailin Wang",
      "affiliations": []
    }
  ],
  "journal": {
    "title": "Optics letters",
    "iso_abbreviation": "Opt Lett",
    "issn": "0146-9592",
    "issn_type": "Print",
    "volume": "28",
    "issue": "10",
    "pub_year": "2003",
    "pub_month": "May",
    "pub_day": "15"
  },
  "start_page": "831",
  "end_page": "833",
  "pages": "831-3",
  "language": "eng",
  "publication_types": [
    "Journal Article"
  ],
  "keywords": [],
  "article_ids": {
    "pubmed": "12779161",
    "doi": "10.1364/ol.28.000831"
  },
  "doi": "10.1364/ol.28.000831",
  "dates": {
    "completed": "2003-06-24",
    "revised": "2019-07-03"
  },
  "chemicals": [],
  "grants": [],
  "search_metadata": {
    "search_type": "all_publications",
    "retrieved_date": "2025-07-30T14:52:16.669291",
    "pmid": "12779161"
  }
}