{
  "pmid": "28668141",
  "uid": "28668141",
  "title": "High-Sensitivity Cardiac Troponin Risk Cutoffs for Acute Cardiac Outcomes at Emergency Department Presentation.",
  "abstract": "The optimal high-sensitivity cardiac troponin (hs-cTn) cutoffs for determining risk in patients who present with acute coronary syndrome symptoms are unknown. In 1137 emergency department patients we calculated adjusted relative risks for a composite outcome (myocardial infarction, unstable angina, heart failure, ventricular arrhythmia, or cardiovascular death) within 7 days for the presentation of hs-cTnT (Roche) and hs-cTnI (Abbott) assay concentrations on the basis of literature cutoffs. Patients with hs-cTn concentrations ≥ 14 ng/L had an adjusted relative risk of 4.9 for the composite outcome, with different hs-cTnT/hs-cTnI concentration ranges yielding higher risks. A common low-risk cutoff of 14 ng/L may be used for hs-cTn with higher cutoffs identifying high-risk patients.",
  "authors": [
    {
      "last_name": "Kavsak",
      "fore_name": "Peter A",
      "initials": "PA",
      "name": "Peter A Kavsak",
      "affiliations": [
        "Department of Pathology and Molecular Medicine, McMaster University, Hamilton, Ontario, Canada. Electronic address: kavsakp@mcmaster.ca."
      ]
    },
    {
      "last_name": "Worster",
      "fore_name": "Andrew",
      "initials": "A",
      "name": "Andrew Worster",
      "affiliations": [
        "Division of Emergency Medicine, McMaster University, Hamilton, Ontario, Canada."
      ]
    },
    {
      "last_name": "Ma",
      "fore_name": "Jinhui",
      "initials": "J",
      "name": "Jinhui Ma",
      "affiliations": [
        "School of Epidemiology, Public Health and Preventive Medicine, University of Ottawa, and the Children's Hospital of Eastern Ontario Research Institute, Ottawa, Ontario, Canada."
      ]
    },
    {
      "last_name": "Shortt",
      "fore_name": "Colleen",
      "initials": "C",
      "name": "Colleen Shortt",
      "affiliations": [
        "Department of Pathology and Molecular Medicine, McMaster University, Hamilton, Ontario, Canada."
      ]
    },
    {
      "last_name": "Clayton",
      "fore_name": "Natasha",
      "initials": "N",
      "name": "Natasha Clayton",
      "affiliations": [
        "Department of Medicine, McMaster University, Hamilton, Ontario, Canada."
      ]
    },
    {
      "last_name": "Sherbino",
      "fore_name": "Jonathan",
      "initials": "J",
      "name": "Jonathan Sherbino",
      "affiliations": [
        "Division of Emergency Medicine, McMaster University, Hamilton, Ontario, Canada."
      ]
    },
    {
      "last_name": "Hill",
      "fore_name": "Stephen A",
      "initials": "SA",
      "name": "Stephen A Hill",
      "affiliations": [
        "Department of Pathology and Molecular Medicine, McMaster University, Hamilton, Ontario, Canada."
      ]
    },
    {
      "last_name": "McQueen",
      "fore_name": "Matthew",
      "initials": "M",
      "name": "Matthew McQueen",
      "affiliations": [
        "Department of Pathology and Molecular Medicine, McMaster University, Hamilton, Ontario, Canada."
      ]
    },
    {
      "last_name": "Mehta",
      "fore_name": "Shamir R",
      "initials": "SR",
      "name": "Shamir R Mehta",
      "affiliations": [
        "Division of Cardiology, and Population Health Research Institute, McMaster University, Hamilton, Ontario, Canada."
      ]
    },
    {
      "last_name": "Devereaux",
      "fore_name": "Philip J",
      "initials": "PJ",
      "name": "Philip J Devereaux",
      "affiliations": [
        "Division of Cardiology, and Population Health Research Institute, McMaster University, Hamilton, Ontario, Canada."
      ]
    }
  ],
  "journal": {
    "title": "The Canadian journal of cardiology",
    "iso_abbreviation": "Can J Cardiol",
    "issn": "1916-7075",
    "issn_type": "Electronic",
    "volume": "33",
    "issue": "7",
    "pub_year": "2017",
    "pub_month": "Jul"
  },
  "start_page": "898",
  "end_page": "903",
  "pages": "898-903",
  "language": "eng",
  "publication_types": [
    "Clinical Trial",
    "Journal Article",
    "Multicenter Study",
    "Research Support, Non-U.S. Gov't"
  ],
  "keywords": [
    "Acute Disease",
    "Biomarkers",
    "Cause of Death",
    "Emergency Service, Hospital",
    "Follow-Up Studies",
    "Heart Diseases",
    "Humans",
    "Incidence",
    "Ontario",
    "Prevalence",
    "Prospective Studies",
    "ROC Curve",
    "Reproducibility of Results",
    "Risk Factors",
    "Survival Rate",
    "Troponin I"
  ],
  "article_ids": {
    "pubmed": "28668141",
    "doi": "10.1016/j.cjca.2017.04.011",
    "pii": "S0828-282X(17)30203-9"
  },
  "doi": "10.1016/j.cjca.2017.04.011",
  "dates": {
    "completed": "2017-09-01",
    "revised": "2018-06-01"
  },
  "chemicals": [
    "Biomarkers",
    "Troponin I"
  ],
  "grants": [
    {
      "agency": "CIHR",
      "country": "Canada"
    }
  ],
  "search_metadata": {
    "search_type": "current_affiliation",
    "retrieved_date": "2025-07-30T14:43:18.778500",
    "pmid": "28668141"
  }
}