{
  "pmid": "28864066",
  "uid": "28864066",
  "title": "Angulation, contact point, and cementoenamel junction distance of impacted mandibular third molars referred for extraction are probably associated with distal caries in the second molar.",
  "abstract": "",
  "authors": [
    {
      "last_name": "Brignardello-Petersen",
      "fore_name": "Romina",
      "initials": "R",
      "name": "Romina Brignardello-Petersen",
      "affiliations": []
    }
  ],
  "journal": {
    "title": "Journal of the American Dental Association (1939)",
    "iso_abbreviation": "J Am Dent Assoc",
    "issn": "1943-4723",
    "issn_type": "Electronic",
    "volume": "148",
    "issue": "11",
    "pub_year": "2017",
    "pub_month": "Nov"
  },
  "start_page": "e168",
  "pages": "e168",
  "language": "eng",
  "publication_types": [
    "Journal Article",
    "Comment"
  ],
  "keywords": [],
  "article_ids": {
    "pubmed": "28864066",
    "doi": "10.1016/j.adaj.2017.08.004",
    "pii": "S0002-8177(17)30706-7"
  },
  "doi": "10.1016/j.adaj.2017.08.004",
  "dates": {
    "revised": "2019-11-20"
  },
  "chemicals": [],
  "grants": [],
  "search_metadata": {
    "search_type": "all_publications",
    "retrieved_date": "2025-07-30T14:10:41.594610",
    "pmid": "28864066"
  }
}